src/__init__.py
src/core/__init__.py
src/core/context.py
src/core/io.py
src/core/scanner.py
src/core/task.py
src/core/workflow.py
src/exceptions/__init__.py
src/exceptions/workflow_exceptions.py
src/utils/__init__.py
src/utils/logging.py
src/utils/validation.py
at_async_workflow-1.0.1.dist-info/METADATA
at_async_workflow-1.0.1.dist-info/WHEEL
at_async_workflow-1.0.1.dist-info/top_level.txt
at_async_workflow-1.0.1.dist-info/RECORD
