Metadata-Version: 2.1
Name: at_async_workflow
Version: 1.0.1
Summary: A robust, asynchronous workflow management system for Python that enables the creation and execution of complex task dependencies using a Directed Acyclic Graph (DAG) approach
Project-URL: Homepage, https://github.com/apex-trader/at-common-workflow
Project-URL: Bug Tracker, https://github.com/apex-trader/at-common-workflow/issues
Requires-Python: >=3.11
Requires-Dist: iniconfig==2.0.0
Requires-Dist: packaging==24.2
Requires-Dist: pluggy==1.5.0
Requires-Dist: pytest==8.3.3
Requires-Dist: pytest-asyncio==0.24.0
Requires-Dist: pydantic==2.10.0
Requires-Dist: pydantic_core==2.27.0
Requires-Dist: tomli==2.1.0
